{
  "id": "GwSSOcubwJyra7n",
  "unique_key": "https://crawlee.dev/python/docs/examples",
  "order_no": null,
  "handled_at": "2026-02-05 09:41:53.044591+00:00",
  "request": {
    "url": "https://crawlee.dev/python/docs/examples",
    "method": "GET",
    "headers": {},
    "payload": null,
    "user_data": {
      "__crawlee": {
        "state": 3
      },
      "label": "HARD"
    },
    "retry_count": 0,
    "no_retry": false,
    "loaded_url": "https://crawlee.dev/python/docs/examples",
    "handled_at": "2026-02-05 09:41:53.044591+00:00",
    "unique_key": "https://crawlee.dev/python/docs/examples",
    "id": "GwSSOcubwJyra7n"
  }
}